cookiecutter.json
fastapi_cookiecutter/__init__.py
fastapi_cookiecutter/main.py
hooks/post_gen_project.py
hooks/pre_gen_project.py
{{cookiecutter.project_slug}}/.coveragerc
{{cookiecutter.project_slug}}/.github/workflows/build.yml
{{cookiecutter.project_slug}}/.github/workflows/sphinx.yml
{{cookiecutter.project_slug}}/.github/workflows/test.yml
{{cookiecutter.project_slug}}/.gitignore
{{cookiecutter.project_slug}}/.gitlab-ci.yml
{{cookiecutter.project_slug}}/CONTRIBUTING.rst
{{cookiecutter.project_slug}}/LICENSES/2-Clause BSD
{{cookiecutter.project_slug}}/LICENSES/3-Clause BSD
{{cookiecutter.project_slug}}/LICENSES/APACHE
{{cookiecutter.project_slug}}/LICENSES/GPL
{{cookiecutter.project_slug}}/LICENSES/MIT
{{cookiecutter.project_slug}}/MANIFEST.in
{{cookiecutter.project_slug}}/Makefile
{{cookiecutter.project_slug}}/README.rst
{{cookiecutter.project_slug}}/bitbucket-pipelines.yml
{{cookiecutter.project_slug}}/docker/Dockerfile
{{cookiecutter.project_slug}}/docker/Dockerfile.local
{{cookiecutter.project_slug}}/docker/compose_hooks/post_build.sh
{{cookiecutter.project_slug}}/docker/compose_hooks/pre_build.sh
{{cookiecutter.project_slug}}/docker/docker-compose.yml
{{cookiecutter.project_slug}}/docker/init.sql
{{cookiecutter.project_slug}}/docker-compose.sh
{{cookiecutter.project_slug}}/docs/Makefile
{{cookiecutter.project_slug}}/docs/make.bat
{{cookiecutter.project_slug}}/docs/source/01_about.rst
{{cookiecutter.project_slug}}/docs/source/02_usage.rst
{{cookiecutter.project_slug}}/docs/source/03_source.rst
{{cookiecutter.project_slug}}/docs/source/04_authors.rst
{{cookiecutter.project_slug}}/docs/source/05_contributing.rst
{{cookiecutter.project_slug}}/docs/source/conf.py
{{cookiecutter.project_slug}}/docs/source/index.rst
{{cookiecutter.project_slug}}/requirements/base.txt
{{cookiecutter.project_slug}}/requirements/dev.txt
{{cookiecutter.project_slug}}/requirements/doc.txt
{{cookiecutter.project_slug}}/scripts/.keep
{{cookiecutter.project_slug}}/scripts/prestart.sh
fastapi_cookiecutter-0.1.2.dist-info/LICENSE
fastapi_cookiecutter-0.1.2.dist-info/METADATA
fastapi_cookiecutter-0.1.2.dist-info/WHEEL
fastapi_cookiecutter-0.1.2.dist-info/entry_points.txt
fastapi_cookiecutter-0.1.2.dist-info/RECORD
