Metadata-Version: 2.1
Name: FastAPI-Cookiecutter
Version: 0.1.2
Summary: This projects consist of a cookiecutter template that generates a full structure for a creating a PyPi standard package.
Home-page: https://github.com/zhiwei2017/fastapi-cookiecutter
License: MIT
Keywords: cookiecutter template,python37,python38,python39,python310,python311,github-actions,gitlab-ci,bitbucket-pipelines,fastapi,RESTful API
Author: Zhiwei Zhang
Author-email: zhiwei2017@gmail.com
Requires-Python: >=3.7,<4.0
Classifier: License :: OSI Approved :: MIT License
Classifier: Programming Language :: Python :: 3
Classifier: Programming Language :: Python :: 3.7
Classifier: Programming Language :: Python :: 3.8
Classifier: Programming Language :: Python :: 3.9
Classifier: Programming Language :: Python :: 3.10
Classifier: Programming Language :: Python :: 3.11
Classifier: Programming Language :: Python :: 3.12
Requires-Dist: cookiecutter (>=2.1,<2.2)
Project-URL: Documentation, https://zhiwei2017.github.io/fastapi-cookiecutter/
Project-URL: Repository, https://github.com/zhiwei2017/fastapi-cookiecutter
